googleaistudio/README.md
googleaistudio/codey.py
googleaistudio/config.py
googleaistudio/geminipro.py
googleaistudio/geminiprovision.py
googleaistudio/health_check.py
googleaistudio/palm2.py
googleaistudio/requirements.txt
googleaistudio/streaming_word_wrapper.py
googleaistudio/utils/prompt_shared_key_bindings.py
googleaistudio/utils/streaming_word_wrapper.py
googleaistudio/utils/tts_utils.py
googleaistudio/utils/vlc_utils.py
googleaistudio-0.0.22.dist-info/METADATA
googleaistudio-0.0.22.dist-info/WHEEL
googleaistudio-0.0.22.dist-info/entry_points.txt
googleaistudio-0.0.22.dist-info/top_level.txt
googleaistudio-0.0.22.dist-info/RECORD
