Metadata-Version: 2.1
Name: googleaistudio
Version: 0.0.22
Summary: Gemini Pro & PaLM 2. A collection of AI tools built on Google Vertex AI APIs. These are part of integrated tools, developed in LetMeDoIt AI project.
Home-page: https://letmedoit.ai
Author: Eliran Wong
Author-email: support@letmedoit.ai
License: GNU General Public License (GPL)
Project-URL: Source, https://github.com/eliranwong/googleaistudio
Project-URL: Tracker, https://github.com/eliranwong/googleaistudio/issues
Project-URL: Documentation, https://github.com/eliranwong/googleaistudio/wiki
Project-URL: Funding, https://www.paypal.me/MarvelBible
Keywords: ai google gemini palm codey vertex api multimodal vision
Classifier: Development Status :: 5 - Production/Stable
Classifier: Intended Audience :: End Users/Desktop
Classifier: Topic :: Utilities
Classifier: License :: OSI Approved :: GNU General Public License v3 or later (GPLv3+)
Classifier: Programming Language :: Python :: 3.8
Classifier: Programming Language :: Python :: 3.9
Classifier: Programming Language :: Python :: 3.10
Classifier: Programming Language :: Python :: 3.11
Classifier: Programming Language :: Python :: 3.12
Requires-Python: >=3.8
Requires-Dist: google-cloud-aiplatform
Requires-Dist: prompt-toolkit
Requires-Dist: Pygments
Requires-Dist: pyperclip
Requires-Dist: argparse
Requires-Dist: pillow
Requires-Dist: requests
Requires-Dist: gTTS
Requires-Dist: pygame
